syntax_symphony/__init__.py
syntax_symphony/cli.py
syntax_symphony/derivation_tree.py
syntax_symphony/fuzzer.py
syntax_symphony/grammar.py
syntax_symphony-0.1.0.dist-info/LICENSE
syntax_symphony-0.1.0.dist-info/METADATA
syntax_symphony-0.1.0.dist-info/WHEEL
syntax_symphony-0.1.0.dist-info/entry_points.txt
syntax_symphony-0.1.0.dist-info/top_level.txt
syntax_symphony-0.1.0.dist-info/RECORD
