Metadata-Version: 2.1
Name: syntax_symphony
Version: 0.1.0
Summary: Efficient grammar-based fuzzer.
Author: Stanimir Iglev
Author-email: Stanimir Iglev <iglev.stanimir@gmail.com>
Maintainer-email: Stanimir Iglev <iglev.stanimir@gmail.com>
License: 
Project-URL: Homepage, https://github.com/StanimirIglev/syntax-symphony
Project-URL: Documentation, https://github.com/StanimirIglev/syntax-symphony/blob/master/README.md
Project-URL: Repository, https://github.com/StanimirIglev/syntax-symphony
Project-URL: Changelog, https://github.com/StanimirIglev/syntax-symphony/blob/master/CHANGELOG.md
Keywords: fuzzer,fuzzing,testing,grammar,grammars
Classifier: Operating System :: OS Independent
Classifier: Programming Language :: Python :: 3
Classifier: Programming Language :: Python :: 3.10
Classifier: Development Status :: 3 - Alpha
Classifier: Topic :: Software Development
Classifier: Topic :: Software Development :: Quality Assurance
Classifier: Topic :: Software Development :: Testing
Classifier: Topic :: Security
Classifier: Topic :: Utilities
Classifier: Intended Audience :: Developers
Requires-Python: >=3.10
License-File: LICENSE
Requires-Dist: schema >=0.7.7
